env3/__init__.py
env3-0.0.6.dist-info/licenses/LICENSE
env3-0.0.6.dist-info/METADATA
env3-0.0.6.dist-info/WHEEL
env3-0.0.6.dist-info/top_level.txt
env3-0.0.6.dist-info/RECORD
