Metadata-Version: 2.4
Name: env3
Version: 0.0.6
Summary: Read .env file
Home-page: https://github.com/hailiang-wang/python-env3
Author: Hai Liang Wang
Author-email: hailiang.hl.wang@gmail.com
License: Chunsong Public License, version 1.0
Keywords: env
Classifier: Intended Audience :: Developers
Classifier: Operating System :: OS Independent
Classifier: Natural Language :: Chinese (Simplified)
Classifier: Natural Language :: Chinese (Traditional)
Classifier: Programming Language :: Python
Classifier: Programming Language :: Python :: 3
Classifier: Programming Language :: Python :: 3.11
License-File: LICENSE
Dynamic: author
Dynamic: author-email
Dynamic: classifier
Dynamic: description
Dynamic: home-page
Dynamic: keywords
Dynamic: license
Dynamic: license-file
Dynamic: summary
